smb3_eh_manip/main.py
smb3_eh_manip/__init__.py
smb3_eh_manip/app/controller.py
smb3_eh_manip/app/eh.py
smb3_eh_manip/app/lsfr.py
smb3_eh_manip/app/models.py
smb3_eh_manip/app/nohands.py
smb3_eh_manip/app/opencv.py
smb3_eh_manip/app/state.py
smb3_eh_manip/app/__init__.py
smb3_eh_manip/app/hbs/hb.py
smb3_eh_manip/app/hbs/w1_bro_left.py
smb3_eh_manip/app/hbs/w1_hb_test.py
smb3_eh_manip/app/hbs/w3_bro_down.py
smb3_eh_manip/app/hbs/w4_cloud_bro_manip.py
smb3_eh_manip/app/hbs/__init__.py
smb3_eh_manip/app/servers/fceux_lua_server.py
smb3_eh_manip/app/servers/livesplit_smb3manip.py
smb3_eh_manip/app/servers/livesplit_wpipe.py
smb3_eh_manip/app/servers/serial_server.py
smb3_eh_manip/app/servers/__init__.py
smb3_eh_manip/ui/audio_player.py
smb3_eh_manip/ui/ui_player.py
smb3_eh_manip/ui/video_player.py
smb3_eh_manip/ui/__init__.py
smb3_eh_manip/util/events.py
smb3_eh_manip/util/logging.py
smb3_eh_manip/util/settings.py
smb3_eh_manip/util/wizard_mixins.py
smb3_eh_manip/util/wpipe.py
smb3_eh_manip/util/__init__.py
smb3_eh_manip-1.3.0.dist-info/METADATA
smb3_eh_manip-1.3.0.dist-info/metadata.json
smb3_eh_manip-1.3.0.dist-info/RECORD
smb3_eh_manip-1.3.0.dist-info/top_level.txt
smb3_eh_manip-1.3.0.dist-info/WHEEL
smb3_eh_manip-1.3.0.dist-info/zip-safe
tests/__init__.py
tests/app/test_eh.py
tests/app/test_lsfr.py
tests/app/test_models.py
tests/app/test_nohands.py
tests/app/test_state.py
tests/app/__init__.py
tests/app/hbs/test_w1_hb_test.py
tests/app/hbs/test_w3_bro_down.py
tests/app/hbs/__init__.py
tests/util/test_events.py
tests/util/test_logging.py
tests/util/__init__.py
