Metadata-Version: 2.0
Name: smb3-eh-manip
Version: 1.3.0
Summary: Ingest video data to render smb3 eh manip stimuli
Author: Jon Robison
Author-email: narfman0@blastedstudios.com
License: LICENSE
Keywords: smb3-eh-manip
Classifier: Development Status :: 4 - Beta
Classifier: License :: OSI Approved :: GNU General Public License v3 (GPLv3)
Classifier: Operating System :: OS Independent
Classifier: Programming Language :: Python
Classifier: Topic :: Software Development :: Libraries :: Python Modules
License-File: LICENSE
Requires-Dist: dataclass-wizard
Requires-Dist: opencv-python
Requires-Dist: pydispatcher
Requires-Dist: pygame
Requires-Dist: pygrabber
Requires-Dist: pyserial
Requires-Dist: python-vlc
Requires-Dist: pyyaml
